<?xml version="1.0" encoding="UTF-8"?>
<!DOCTYPE LCTL_TEXT SYSTEM "ltf.v1.5.dtd">
<LCTL_TEXT>
<DOC id="CMN_NW_001330_20150714_F0010001C.nw.xml" tokenization="tokenization_parameters" grammar="none" raw_text_char_length="704" raw_text_md5="caf0b072526b0d50ec2eaed9ca8909a1">
<TEXT>
<SEG id="segment-0" start_char="0" end_char="37">
<ORIGINAL_TEXT>&lt;?xml version="1.0" encoding="utf-8"?&gt;</ORIGINAL_TEXT>
<TOKEN id="token-0-0" pos="unknown" morph="none" start_char="0" end_char="4">&lt;?xml</TOKEN>
<TOKEN id="token-0-1" pos="unknown" morph="none" start_char="6" end_char="18">version="1.0"</TOKEN>
<TOKEN id="token-0-2" pos="unknown" morph="none" start_char="20" end_char="37">encoding="utf-8"?&gt;</TOKEN>
</SEG>
<SEG id="segment-1" start_char="39" end_char="81">
<ORIGINAL_TEXT>&lt;DOC id="CMN_NW_001330_20150714_F0010001C"&gt;</ORIGINAL_TEXT>
<TOKEN id="token-1-0" pos="unknown" morph="none" start_char="39" end_char="42">&lt;DOC</TOKEN>
<TOKEN id="token-1-1" pos="unknown" morph="none" start_char="44" end_char="81">id="CMN_NW_001330_20150714_F0010001C"&gt;</TOKEN>
</SEG>
<SEG id="segment-2" start_char="83" end_char="176">
<ORIGINAL_TEXT>&lt;SOURCE&gt;http://www.aboluowang.com/2015/0714/584501.html#sthash.ZFCiL665.QYIbrZVA.dpbs&lt;/SOURCE&gt;</ORIGINAL_TEXT>
<TOKEN id="token-2-0" pos="unknown" morph="none" start_char="83" end_char="176">&lt;SOURCE&gt;http://www.aboluowang.com/2015/0714/584501.html#sthash.ZFCiL665.QYIbrZVA.dpbs&lt;/SOURCE&gt;</TOKEN>
</SEG>
<SEG id="segment-3" start_char="178" end_char="219">
<ORIGINAL_TEXT>&lt;DATE_TIME&gt;2015-07-14T00:00:00&lt;/DATE_TIME&gt;</ORIGINAL_TEXT>
<TOKEN id="token-3-0" pos="unknown" morph="none" start_char="178" end_char="219">&lt;DATE_TIME&gt;2015-07-14T00:00:00&lt;/DATE_TIME&gt;</TOKEN>
</SEG>
<SEG id="segment-4" start_char="221" end_char="230">
<ORIGINAL_TEXT>&lt;HEADLINE&gt;</ORIGINAL_TEXT>
<TOKEN id="token-4-0" pos="unknown" morph="none" start_char="221" end_char="230">&lt;HEADLINE&gt;</TOKEN>
</SEG>
<SEG id="segment-5" start_char="232" end_char="248">
<ORIGINAL_TEXT>希腊债务危机：欧元区与希腊达成协议</ORIGINAL_TEXT>
<TOKEN id="token-5-0" pos="word" morph="none" start_char="232" end_char="237">希腊债务危机</TOKEN>
<TOKEN id="token-5-1" pos="punct" morph="none" start_char="238" end_char="238">：</TOKEN>
<TOKEN id="token-5-2" pos="word" morph="none" start_char="239" end_char="248">欧元区与希腊达成协议</TOKEN>
</SEG>
<SEG id="segment-6" start_char="250" end_char="260">
<ORIGINAL_TEXT>&lt;/HEADLINE&gt;</ORIGINAL_TEXT>
<TOKEN id="token-6-0" pos="unknown" morph="none" start_char="250" end_char="260">&lt;/HEADLINE&gt;</TOKEN>
</SEG>
<SEG id="segment-7" start_char="262" end_char="267">
<ORIGINAL_TEXT>&lt;TEXT&gt;</ORIGINAL_TEXT>
<TOKEN id="token-7-0" pos="unknown" morph="none" start_char="262" end_char="267">&lt;TEXT&gt;</TOKEN>
</SEG>
<SEG id="segment-8" start_char="269" end_char="271">
<ORIGINAL_TEXT>&lt;P&gt;</ORIGINAL_TEXT>
<TOKEN id="token-8-0" pos="unknown" morph="none" start_char="269" end_char="271">&lt;P&gt;</TOKEN>
</SEG>
<SEG id="segment-9" start_char="273" end_char="298">
<ORIGINAL_TEXT>图斯克说，经过17个小时之后，欧元区终于达成了协议。</ORIGINAL_TEXT>
<TOKEN id="token-9-0" pos="unknown" morph="none" start_char="273" end_char="298">图斯克说，经过17个小时之后，欧元区终于达成了协议。</TOKEN>
</SEG>
<SEG id="segment-10" start_char="300" end_char="303">
<ORIGINAL_TEXT>&lt;/P&gt;</ORIGINAL_TEXT>
<TOKEN id="token-10-0" pos="unknown" morph="none" start_char="300" end_char="303">&lt;/P&gt;</TOKEN>
</SEG>
<SEG id="segment-11" start_char="305" end_char="307">
<ORIGINAL_TEXT>&lt;P&gt;</ORIGINAL_TEXT>
<TOKEN id="token-11-0" pos="unknown" morph="none" start_char="305" end_char="307">&lt;P&gt;</TOKEN>
</SEG>
<SEG id="segment-12" start_char="309" end_char="359">
<ORIGINAL_TEXT>欧洲理事会主席图斯克宣布，欧元区各国领袖与希腊经过马拉松谈判后，就第三次财政救助希腊达成“一致”协议。</ORIGINAL_TEXT>
<TOKEN id="token-12-0" pos="unknown" morph="none" start_char="309" end_char="359">欧洲理事会主席图斯克宣布，欧元区各国领袖与希腊经过马拉松谈判后，就第三次财政救助希腊达成“一致”协议。</TOKEN>
</SEG>
<SEG id="segment-13" start_char="361" end_char="364">
<ORIGINAL_TEXT>&lt;/P&gt;</ORIGINAL_TEXT>
<TOKEN id="token-13-0" pos="unknown" morph="none" start_char="361" end_char="364">&lt;/P&gt;</TOKEN>
</SEG>
<SEG id="segment-14" start_char="366" end_char="368">
<ORIGINAL_TEXT>&lt;P&gt;</ORIGINAL_TEXT>
<TOKEN id="token-14-0" pos="unknown" morph="none" start_char="366" end_char="368">&lt;P&gt;</TOKEN>
</SEG>
<SEG id="segment-15" start_char="370" end_char="430">
<ORIGINAL_TEXT>图斯克星期一(7月13日)早晨在布鲁塞尔对记者们说，各国领袖“原则上”已同意就财政救助展开谈判，“换言之将继续支持希腊”。</ORIGINAL_TEXT>
<TOKEN id="token-15-0" pos="unknown" morph="none" start_char="370" end_char="430">图斯克星期一(7月13日)早晨在布鲁塞尔对记者们说，各国领袖“原则上”已同意就财政救助展开谈判，“换言之将继续支持希腊”。</TOKEN>
</SEG>
<SEG id="segment-16" start_char="432" end_char="435">
<ORIGINAL_TEXT>&lt;/P&gt;</ORIGINAL_TEXT>
<TOKEN id="token-16-0" pos="unknown" morph="none" start_char="432" end_char="435">&lt;/P&gt;</TOKEN>
</SEG>
<SEG id="segment-17" start_char="437" end_char="439">
<ORIGINAL_TEXT>&lt;P&gt;</ORIGINAL_TEXT>
<TOKEN id="token-17-0" pos="unknown" morph="none" start_char="437" end_char="439">&lt;P&gt;</TOKEN>
</SEG>
<SEG id="segment-18" start_char="441" end_char="498">
<ORIGINAL_TEXT>希腊总理齐普拉斯说，他们已“战斗到底”，成功重组债务结构，确保了中期财政来源。希腊将继续斗争，直到实现恢复经济增长。</ORIGINAL_TEXT>
<TOKEN id="token-18-0" pos="unknown" morph="none" start_char="441" end_char="498">希腊总理齐普拉斯说，他们已“战斗到底”，成功重组债务结构，确保了中期财政来源。希腊将继续斗争，直到实现恢复经济增长。</TOKEN>
</SEG>
<SEG id="segment-19" start_char="500" end_char="503">
<ORIGINAL_TEXT>&lt;/P&gt;</ORIGINAL_TEXT>
<TOKEN id="token-19-0" pos="unknown" morph="none" start_char="500" end_char="503">&lt;/P&gt;</TOKEN>
</SEG>
<SEG id="segment-20" start_char="505" end_char="507">
<ORIGINAL_TEXT>&lt;P&gt;</ORIGINAL_TEXT>
<TOKEN id="token-20-0" pos="unknown" morph="none" start_char="505" end_char="507">&lt;P&gt;</TOKEN>
</SEG>
<SEG id="segment-21" start_char="509" end_char="580">
<ORIGINAL_TEXT>欧洲委员会主席容克则说“Grexit”不会发生，意思是希腊不会退出欧元区;德国总理默克尔说，前路仍然艰巨，但欧元区各国之间现在可以开始重建互信。</ORIGINAL_TEXT>
<TOKEN id="token-21-0" pos="unknown" morph="none" start_char="509" end_char="580">欧洲委员会主席容克则说“Grexit”不会发生，意思是希腊不会退出欧元区;德国总理默克尔说，前路仍然艰巨，但欧元区各国之间现在可以开始重建互信。</TOKEN>
</SEG>
<SEG id="segment-22" start_char="582" end_char="585">
<ORIGINAL_TEXT>&lt;/P&gt;</ORIGINAL_TEXT>
<TOKEN id="token-22-0" pos="unknown" morph="none" start_char="582" end_char="585">&lt;/P&gt;</TOKEN>
</SEG>
<SEG id="segment-23" start_char="587" end_char="589">
<ORIGINAL_TEXT>&lt;P&gt;</ORIGINAL_TEXT>
<TOKEN id="token-23-0" pos="unknown" morph="none" start_char="587" end_char="589">&lt;P&gt;</TOKEN>
</SEG>
<SEG id="segment-24" start_char="591" end_char="640">
<ORIGINAL_TEXT>欧元区领袖已在布鲁塞尔为此谈判超过16个小时。雅典预计将与星期三通过法案，接纳欧元区提出的改革要求。</ORIGINAL_TEXT>
<TOKEN id="token-24-0" pos="unknown" morph="none" start_char="591" end_char="640">欧元区领袖已在布鲁塞尔为此谈判超过16个小时。雅典预计将与星期三通过法案，接纳欧元区提出的改革要求。</TOKEN>
</SEG>
<SEG id="segment-25" start_char="642" end_char="645">
<ORIGINAL_TEXT>&lt;/P&gt;</ORIGINAL_TEXT>
<TOKEN id="token-25-0" pos="unknown" morph="none" start_char="642" end_char="645">&lt;/P&gt;</TOKEN>
</SEG>
<SEG id="segment-26" start_char="647" end_char="649">
<ORIGINAL_TEXT>&lt;P&gt;</ORIGINAL_TEXT>
<TOKEN id="token-26-0" pos="unknown" morph="none" start_char="647" end_char="649">&lt;P&gt;</TOKEN>
</SEG>
<SEG id="segment-27" start_char="651" end_char="682">
<ORIGINAL_TEXT>受达成协议的消息刺激，欧洲多处股市早盘上扬，欧元兑美元先升后跌。</ORIGINAL_TEXT>
<TOKEN id="token-27-0" pos="unknown" morph="none" start_char="651" end_char="682">受达成协议的消息刺激，欧洲多处股市早盘上扬，欧元兑美元先升后跌。</TOKEN>
</SEG>
<SEG id="segment-28" start_char="684" end_char="687">
<ORIGINAL_TEXT>&lt;/P&gt;</ORIGINAL_TEXT>
<TOKEN id="token-28-0" pos="unknown" morph="none" start_char="684" end_char="687">&lt;/P&gt;</TOKEN>
</SEG>
<SEG id="segment-29" start_char="689" end_char="695">
<ORIGINAL_TEXT>&lt;/TEXT&gt;</ORIGINAL_TEXT>
<TOKEN id="token-29-0" pos="unknown" morph="none" start_char="689" end_char="695">&lt;/TEXT&gt;</TOKEN>
</SEG>
<SEG id="segment-30" start_char="697" end_char="702">
<ORIGINAL_TEXT>&lt;/DOC&gt;</ORIGINAL_TEXT>
<TOKEN id="token-30-0" pos="unknown" morph="none" start_char="697" end_char="702">&lt;/DOC&gt;</TOKEN>
</SEG>
</TEXT>
</DOC>
</LCTL_TEXT>
