<?xml version="1.0" encoding="UTF-8"?>
<LCTL_TEXT>
  <DOC id="CMN_NW_001150_20141203_F0000005J.xml" tokenization="tokenization_parameters" grammar="none" raw_text_char_length="677" raw_text_md5="ae0a6f04b329f7293280e69f2787f01e">
    <TEXT>
      <SEG id="segment-0" start_char="0" end_char="37">
        <ORIGINAL_TEXT>&lt;?xml version="1.0" encoding="utf-8"?&gt;</ORIGINAL_TEXT>
        <TOKEN id="token-0-0" pos="unknown" morph="none" start_char="0" end_char="4">&lt;?xml</TOKEN>
        <TOKEN id="token-0-1" pos="unknown" morph="none" start_char="6" end_char="18">version="1.0"</TOKEN>
        <TOKEN id="token-0-2" pos="unknown" morph="none" start_char="20" end_char="37">encoding="utf-8"?&gt;</TOKEN>
      </SEG>
      <SEG id="segment-1" start_char="39" end_char="81">
        <ORIGINAL_TEXT>&lt;DOC id="CMN_NW_001150_20141203_F0000005J"&gt;</ORIGINAL_TEXT>
        <TOKEN id="token-1-0" pos="unknown" morph="none" start_char="39" end_char="42">&lt;DOC</TOKEN>
        <TOKEN id="token-1-1" pos="unknown" morph="none" start_char="44" end_char="81">id="CMN_NW_001150_20141203_F0000005J"&gt;</TOKEN>
      </SEG>
      <SEG id="segment-2" start_char="83" end_char="134">
        <ORIGINAL_TEXT>&lt;SOURCE&gt;http://wallstreetcn.com/node/211484&lt;/SOURCE&gt;</ORIGINAL_TEXT>
        <TOKEN id="token-2-0" pos="unknown" morph="none" start_char="83" end_char="134">&lt;SOURCE&gt;http://wallstreetcn.com/node/211484&lt;/SOURCE&gt;</TOKEN>
      </SEG>
      <SEG id="segment-3" start_char="136" end_char="177">
        <ORIGINAL_TEXT>&lt;DATE_TIME&gt;2014-12-03T00:00:00&lt;/DATE_TIME&gt;</ORIGINAL_TEXT>
        <TOKEN id="token-3-0" pos="unknown" morph="none" start_char="136" end_char="177">&lt;DATE_TIME&gt;2014-12-03T00:00:00&lt;/DATE_TIME&gt;</TOKEN>
      </SEG>
      <SEG id="segment-4" start_char="179" end_char="188">
        <ORIGINAL_TEXT>&lt;HEADLINE&gt;</ORIGINAL_TEXT>
        <TOKEN id="token-4-0" pos="unknown" morph="none" start_char="179" end_char="188">&lt;HEADLINE&gt;</TOKEN>
      </SEG>
      <SEG id="segment-5" start_char="190" end_char="206">
        <ORIGINAL_TEXT>黎巴嫩军方扣留“伊斯兰国”头目妻儿</ORIGINAL_TEXT>
        <TOKEN id="token-5-0" pos="unknown" morph="none" start_char="190" end_char="206">黎巴嫩军方扣留“伊斯兰国”头目妻儿</TOKEN>
      </SEG>
      <SEG id="segment-6" start_char="208" end_char="218">
        <ORIGINAL_TEXT>&lt;/HEADLINE&gt;</ORIGINAL_TEXT>
        <TOKEN id="token-6-0" pos="unknown" morph="none" start_char="208" end_char="218">&lt;/HEADLINE&gt;</TOKEN>
      </SEG>
      <SEG id="segment-7" start_char="220" end_char="225">
        <ORIGINAL_TEXT>&lt;TEXT&gt;</ORIGINAL_TEXT>
        <TOKEN id="token-7-0" pos="unknown" morph="none" start_char="220" end_char="225">&lt;TEXT&gt;</TOKEN>
      </SEG>
      <SEG id="segment-8" start_char="227" end_char="229">
        <ORIGINAL_TEXT>&lt;P&gt;</ORIGINAL_TEXT>
        <TOKEN id="token-8-0" pos="unknown" morph="none" start_char="227" end_char="229">&lt;P&gt;</TOKEN>
      </SEG>
      <SEG id="segment-9" start_char="231" end_char="291">
        <ORIGINAL_TEXT>据英国《金融时报》援引黎巴嫩安全部消息人士称，黎巴嫩军方已扣押伊斯兰国（ISIS）组织领导人阿布•贝克尔•巴格达迪（Abu</ORIGINAL_TEXT>
        <TOKEN id="token-9-0" pos="unknown" morph="none" start_char="231" end_char="291">据英国《金融时报》援引黎巴嫩安全部消息人士称，黎巴嫩军方已扣押伊斯兰国（ISIS）组织领导人阿布•贝克尔•巴格达迪（Abu</TOKEN>
      </SEG>
      <SEG id="segment-10" start_char="293" end_char="296">
        <ORIGINAL_TEXT>Bakr</ORIGINAL_TEXT>
        <TOKEN id="token-10-0" pos="word" morph="none" start_char="293" end_char="296">Bakr</TOKEN>
      </SEG>
      <SEG id="segment-11" start_char="298" end_char="335">
        <ORIGINAL_TEXT>al-Baghdadi）的妻子和儿子，两人目前被关在黎巴嫩国防部，接受讯问。</ORIGINAL_TEXT>
        <TOKEN id="token-11-0" pos="unknown" morph="none" start_char="298" end_char="335">al-Baghdadi）的妻子和儿子，两人目前被关在黎巴嫩国防部，接受讯问。</TOKEN>
      </SEG>
      <SEG id="segment-12" start_char="337" end_char="340">
        <ORIGINAL_TEXT>&lt;/P&gt;</ORIGINAL_TEXT>
        <TOKEN id="token-12-0" pos="unknown" morph="none" start_char="337" end_char="340">&lt;/P&gt;</TOKEN>
      </SEG>
      <SEG id="segment-13" start_char="342" end_char="344">
        <ORIGINAL_TEXT>&lt;P&gt;</ORIGINAL_TEXT>
        <TOKEN id="token-13-0" pos="unknown" morph="none" start_char="342" end_char="344">&lt;P&gt;</TOKEN>
      </SEG>
      <SEG id="segment-14" start_char="346" end_char="451">
        <ORIGINAL_TEXT>巴格达迪的妻子和儿子大约10天前在叙利亚边界附近被扣留。据黎巴嫩《使者报》报道，黎巴嫩情报部门在外国情报机构的配合下，于日前在黎叙边境口岸成功抓捕了巴格达迪的妻子和一个儿子。他们当时正企图用假证件进入黎巴嫩境内。</ORIGINAL_TEXT>
        <TOKEN id="token-14-0" pos="unknown" morph="none" start_char="346" end_char="451">巴格达迪的妻子和儿子大约10天前在叙利亚边界附近被扣留。据黎巴嫩《使者报》报道，黎巴嫩情报部门在外国情报机构的配合下，于日前在黎叙边境口岸成功抓捕了巴格达迪的妻子和一个儿子。他们当时正企图用假证件进入黎巴嫩境内。</TOKEN>
      </SEG>
      <SEG id="segment-15" start_char="453" end_char="456">
        <ORIGINAL_TEXT>&lt;/P&gt;</ORIGINAL_TEXT>
        <TOKEN id="token-15-0" pos="unknown" morph="none" start_char="453" end_char="456">&lt;/P&gt;</TOKEN>
      </SEG>
      <SEG id="segment-16" start_char="458" end_char="460">
        <ORIGINAL_TEXT>&lt;P&gt;</ORIGINAL_TEXT>
        <TOKEN id="token-16-0" pos="unknown" morph="none" start_char="458" end_char="460">&lt;P&gt;</TOKEN>
      </SEG>
      <SEG id="segment-17" start_char="462" end_char="581">
        <ORIGINAL_TEXT>巴格达迪自2010年以来一直领导着伊斯兰国组织。他今年年初宣布在伊斯兰国激进分子占据的叙利亚东部和伊拉克北部地区建立“哈里发国”。美国已宣布巴格达迪为全球恐怖分子，并悬赏1千万美元捉拿他。上月9日，伊拉克内政部称，巴格达迪在一次空袭中受伤。</ORIGINAL_TEXT>
        <TOKEN id="token-17-0" pos="unknown" morph="none" start_char="462" end_char="581">巴格达迪自2010年以来一直领导着伊斯兰国组织。他今年年初宣布在伊斯兰国激进分子占据的叙利亚东部和伊拉克北部地区建立“哈里发国”。美国已宣布巴格达迪为全球恐怖分子，并悬赏1千万美元捉拿他。上月9日，伊拉克内政部称，巴格达迪在一次空袭中受伤。</TOKEN>
      </SEG>
      <SEG id="segment-18" start_char="583" end_char="586">
        <ORIGINAL_TEXT>&lt;/P&gt;</ORIGINAL_TEXT>
        <TOKEN id="token-18-0" pos="unknown" morph="none" start_char="583" end_char="586">&lt;/P&gt;</TOKEN>
      </SEG>
      <SEG id="segment-19" start_char="588" end_char="590">
        <ORIGINAL_TEXT>&lt;P&gt;</ORIGINAL_TEXT>
        <TOKEN id="token-19-0" pos="unknown" morph="none" start_char="588" end_char="590">&lt;P&gt;</TOKEN>
      </SEG>
      <SEG id="segment-20" start_char="592" end_char="655">
        <ORIGINAL_TEXT>美国国务卿约翰•克里周三将出席在布鲁塞尔召开的部长级会议。60个联盟伙伴国家将在会议上讨论如何针对打击伊斯兰国组织做出政治努力。</ORIGINAL_TEXT>
        <TOKEN id="token-20-0" pos="unknown" morph="none" start_char="592" end_char="655">美国国务卿约翰•克里周三将出席在布鲁塞尔召开的部长级会议。60个联盟伙伴国家将在会议上讨论如何针对打击伊斯兰国组织做出政治努力。</TOKEN>
      </SEG>
      <SEG id="segment-21" start_char="657" end_char="660">
        <ORIGINAL_TEXT>&lt;/P&gt;</ORIGINAL_TEXT>
        <TOKEN id="token-21-0" pos="unknown" morph="none" start_char="657" end_char="660">&lt;/P&gt;</TOKEN>
      </SEG>
      <SEG id="segment-22" start_char="662" end_char="668">
        <ORIGINAL_TEXT>&lt;/TEXT&gt;</ORIGINAL_TEXT>
        <TOKEN id="token-22-0" pos="unknown" morph="none" start_char="662" end_char="668">&lt;/TEXT&gt;</TOKEN>
      </SEG>
      <SEG id="segment-23" start_char="670" end_char="675">
        <ORIGINAL_TEXT>&lt;/DOC&gt;</ORIGINAL_TEXT>
        <TOKEN id="token-23-0" pos="unknown" morph="none" start_char="670" end_char="675">&lt;/DOC&gt;</TOKEN>
      </SEG>
    </TEXT>
  </DOC>
</LCTL_TEXT>
