<?xml version="1.0" encoding="UTF-8"?>
<LCTL_TEXT>
  <DOC id="CMN_NW_001168_20150405_F00000067.xml" tokenization="tokenization_parameters" grammar="none" raw_text_char_length="1000" raw_text_md5="886569118efdc288837b705bef7a0ab7">
    <TEXT>
      <SEG id="segment-0" start_char="0" end_char="37">
        <ORIGINAL_TEXT>&lt;?xml version="1.0" encoding="utf-8"?&gt;</ORIGINAL_TEXT>
        <TOKEN id="token-0-0" pos="unknown" morph="none" start_char="0" end_char="4">&lt;?xml</TOKEN>
        <TOKEN id="token-0-1" pos="unknown" morph="none" start_char="6" end_char="18">version="1.0"</TOKEN>
        <TOKEN id="token-0-2" pos="unknown" morph="none" start_char="20" end_char="37">encoding="utf-8"?&gt;</TOKEN>
      </SEG>
      <SEG id="segment-1" start_char="39" end_char="81">
        <ORIGINAL_TEXT>&lt;DOC id="CMN_NW_001168_20150405_F00000067"&gt;</ORIGINAL_TEXT>
        <TOKEN id="token-1-0" pos="unknown" morph="none" start_char="39" end_char="42">&lt;DOC</TOKEN>
        <TOKEN id="token-1-1" pos="unknown" morph="none" start_char="44" end_char="81">id="CMN_NW_001168_20150405_F00000067"&gt;</TOKEN>
      </SEG>
      <SEG id="segment-2" start_char="83" end_char="149">
        <ORIGINAL_TEXT>&lt;SOURCE&gt;http://www.hkcna.hk/content/2015/0405/354855.shtml&lt;/SOURCE&gt;</ORIGINAL_TEXT>
        <TOKEN id="token-2-0" pos="unknown" morph="none" start_char="83" end_char="149">&lt;SOURCE&gt;http://www.hkcna.hk/content/2015/0405/354855.shtml&lt;/SOURCE&gt;</TOKEN>
      </SEG>
      <SEG id="segment-3" start_char="151" end_char="192">
        <ORIGINAL_TEXT>&lt;DATE_TIME&gt;2015-04-05T00:00:00&lt;/DATE_TIME&gt;</ORIGINAL_TEXT>
        <TOKEN id="token-3-0" pos="unknown" morph="none" start_char="151" end_char="192">&lt;DATE_TIME&gt;2015-04-05T00:00:00&lt;/DATE_TIME&gt;</TOKEN>
      </SEG>
      <SEG id="segment-4" start_char="194" end_char="203">
        <ORIGINAL_TEXT>&lt;HEADLINE&gt;</ORIGINAL_TEXT>
        <TOKEN id="token-4-0" pos="unknown" morph="none" start_char="194" end_char="203">&lt;HEADLINE&gt;</TOKEN>
      </SEG>
      <SEG id="segment-5" start_char="205" end_char="217">
        <ORIGINAL_TEXT>肯尼亞大學恐襲148人死亡</ORIGINAL_TEXT>
        <TOKEN id="token-5-0" pos="word" morph="none" start_char="205" end_char="217">肯尼亞大學恐襲148人死亡</TOKEN>
      </SEG>
      <SEG id="segment-6" start_char="219" end_char="229">
        <ORIGINAL_TEXT>&lt;/HEADLINE&gt;</ORIGINAL_TEXT>
        <TOKEN id="token-6-0" pos="unknown" morph="none" start_char="219" end_char="229">&lt;/HEADLINE&gt;</TOKEN>
      </SEG>
      <SEG id="segment-7" start_char="231" end_char="236">
        <ORIGINAL_TEXT>&lt;TEXT&gt;</ORIGINAL_TEXT>
        <TOKEN id="token-7-0" pos="unknown" morph="none" start_char="231" end_char="236">&lt;TEXT&gt;</TOKEN>
      </SEG>
      <SEG id="segment-8" start_char="238" end_char="240">
        <ORIGINAL_TEXT>&lt;P&gt;</ORIGINAL_TEXT>
        <TOKEN id="token-8-0" pos="unknown" morph="none" start_char="238" end_char="240">&lt;P&gt;</TOKEN>
      </SEG>
      <SEG id="segment-9" start_char="242" end_char="253">
        <ORIGINAL_TEXT>　　香港中通社4月4日電</ORIGINAL_TEXT>
        <TOKEN id="token-9-0" pos="unknown" morph="none" start_char="242" end_char="253">　　香港中通社4月4日電</TOKEN>
      </SEG>
      <SEG id="segment-10" start_char="255" end_char="313">
        <ORIGINAL_TEXT>綜合外媒報道，肯尼亞加里薩市莫伊大學2日遭武裝分子襲擊，肯尼亞內政部長當地時間3日稱，襲擊事件遇難人數已增至148人。</ORIGINAL_TEXT>
        <TOKEN id="token-10-0" pos="unknown" morph="none" start_char="255" end_char="313">綜合外媒報道，肯尼亞加里薩市莫伊大學2日遭武裝分子襲擊，肯尼亞內政部長當地時間3日稱，襲擊事件遇難人數已增至148人。</TOKEN>
      </SEG>
      <SEG id="segment-11" start_char="315" end_char="318">
        <ORIGINAL_TEXT>&lt;/P&gt;</ORIGINAL_TEXT>
        <TOKEN id="token-11-0" pos="unknown" morph="none" start_char="315" end_char="318">&lt;/P&gt;</TOKEN>
      </SEG>
      <SEG id="segment-12" start_char="320" end_char="322">
        <ORIGINAL_TEXT>&lt;P&gt;</ORIGINAL_TEXT>
        <TOKEN id="token-12-0" pos="unknown" morph="none" start_char="320" end_char="322">&lt;P&gt;</TOKEN>
      </SEG>
      <SEG id="segment-13" start_char="324" end_char="346">
        <ORIGINAL_TEXT>　　肯尼亞內政部長約瑟夫•凱薩利(Joseph</ORIGINAL_TEXT>
        <TOKEN id="token-13-0" pos="unknown" morph="none" start_char="324" end_char="346">　　肯尼亞內政部長約瑟夫•凱薩利(Joseph</TOKEN>
      </SEG>
      <SEG id="segment-14" start_char="348" end_char="389">
        <ORIGINAL_TEXT>Nkaiserry)稱，莫伊大學襲擊事件遇難者包括142名學生、3名警察和3名軍人。</ORIGINAL_TEXT>
        <TOKEN id="token-14-0" pos="unknown" morph="none" start_char="348" end_char="389">Nkaiserry)稱，莫伊大學襲擊事件遇難者包括142名學生、3名警察和3名軍人。</TOKEN>
      </SEG>
      <SEG id="segment-15" start_char="391" end_char="394">
        <ORIGINAL_TEXT>&lt;/P&gt;</ORIGINAL_TEXT>
        <TOKEN id="token-15-0" pos="unknown" morph="none" start_char="391" end_char="394">&lt;/P&gt;</TOKEN>
      </SEG>
      <SEG id="segment-16" start_char="396" end_char="398">
        <ORIGINAL_TEXT>&lt;P&gt;</ORIGINAL_TEXT>
        <TOKEN id="token-16-0" pos="unknown" morph="none" start_char="396" end_char="398">&lt;P&gt;</TOKEN>
      </SEG>
      <SEG id="segment-17" start_char="400" end_char="431">
        <ORIGINAL_TEXT>　　他還表示，當地警方逮捕了與莫伊大學襲擊事件有關的5名嫌疑人。</ORIGINAL_TEXT>
        <TOKEN id="token-17-0" pos="unknown" morph="none" start_char="400" end_char="431">　　他還表示，當地警方逮捕了與莫伊大學襲擊事件有關的5名嫌疑人。</TOKEN>
      </SEG>
      <SEG id="segment-18" start_char="433" end_char="436">
        <ORIGINAL_TEXT>&lt;/P&gt;</ORIGINAL_TEXT>
        <TOKEN id="token-18-0" pos="unknown" morph="none" start_char="433" end_char="436">&lt;/P&gt;</TOKEN>
      </SEG>
      <SEG id="segment-19" start_char="438" end_char="440">
        <ORIGINAL_TEXT>&lt;P&gt;</ORIGINAL_TEXT>
        <TOKEN id="token-19-0" pos="unknown" morph="none" start_char="438" end_char="440">&lt;P&gt;</TOKEN>
      </SEG>
      <SEG id="segment-20" start_char="442" end_char="621">
        <ORIGINAL_TEXT>　　當地時間2日，肯尼亞東北部加里薩市莫伊大學遭到武裝分子襲擊，造成148人死亡，179受傷，肯尼亞政府軍在營救行動中救出500多人。4名襲擊者全部被擊斃。索馬里極端組織“青年黨”當天承認製造了這起襲擊。這是肯尼亞自2011年出兵索馬里圍剿“青年黨”武裝以來遭遇的最嚴重的恐怖襲擊。2013年9月，“青年黨”曾對內羅畢西門購物中心發動恐怖襲擊，導致67人喪生。</ORIGINAL_TEXT>
        <TOKEN id="token-20-0" pos="unknown" morph="none" start_char="442" end_char="621">　　當地時間2日，肯尼亞東北部加里薩市莫伊大學遭到武裝分子襲擊，造成148人死亡，179受傷，肯尼亞政府軍在營救行動中救出500多人。4名襲擊者全部被擊斃。索馬里極端組織“青年黨”當天承認製造了這起襲擊。這是肯尼亞自2011年出兵索馬里圍剿“青年黨”武裝以來遭遇的最嚴重的恐怖襲擊。2013年9月，“青年黨”曾對內羅畢西門購物中心發動恐怖襲擊，導致67人喪生。</TOKEN>
      </SEG>
      <SEG id="segment-21" start_char="623" end_char="626">
        <ORIGINAL_TEXT>&lt;/P&gt;</ORIGINAL_TEXT>
        <TOKEN id="token-21-0" pos="unknown" morph="none" start_char="623" end_char="626">&lt;/P&gt;</TOKEN>
      </SEG>
      <SEG id="segment-22" start_char="628" end_char="630">
        <ORIGINAL_TEXT>&lt;P&gt;</ORIGINAL_TEXT>
        <TOKEN id="token-22-0" pos="unknown" morph="none" start_char="628" end_char="630">&lt;P&gt;</TOKEN>
      </SEG>
      <SEG id="segment-23" start_char="632" end_char="706">
        <ORIGINAL_TEXT>　　目前，肯尼亞政府已經發出通緝令，懸賞2000萬肯尼亞先令(約合21.7萬美元)通緝一名叫做穆罕默德•庫諾的男子。但并未說明此人在襲擊事件中的角色。</ORIGINAL_TEXT>
        <TOKEN id="token-23-0" pos="unknown" morph="none" start_char="632" end_char="706">　　目前，肯尼亞政府已經發出通緝令，懸賞2000萬肯尼亞先令(約合21.7萬美元)通緝一名叫做穆罕默德•庫諾的男子。但并未說明此人在襲擊事件中的角色。</TOKEN>
      </SEG>
      <SEG id="segment-24" start_char="708" end_char="711">
        <ORIGINAL_TEXT>&lt;/P&gt;</ORIGINAL_TEXT>
        <TOKEN id="token-24-0" pos="unknown" morph="none" start_char="708" end_char="711">&lt;/P&gt;</TOKEN>
      </SEG>
      <SEG id="segment-25" start_char="713" end_char="715">
        <ORIGINAL_TEXT>&lt;P&gt;</ORIGINAL_TEXT>
        <TOKEN id="token-25-0" pos="unknown" morph="none" start_char="713" end_char="715">&lt;P&gt;</TOKEN>
      </SEG>
      <SEG id="segment-26" start_char="717" end_char="780">
        <ORIGINAL_TEXT>　　當地時間4日，索馬里“青年黨”通過電子郵件發佈聲明，威脅將對肯尼亞發起更多襲擊。該聲明稱，肯尼亞將面對“漫長、可怕的戰爭”。</ORIGINAL_TEXT>
        <TOKEN id="token-26-0" pos="unknown" morph="none" start_char="717" end_char="780">　　當地時間4日，索馬里“青年黨”通過電子郵件發佈聲明，威脅將對肯尼亞發起更多襲擊。該聲明稱，肯尼亞將面對“漫長、可怕的戰爭”。</TOKEN>
      </SEG>
      <SEG id="segment-27" start_char="782" end_char="785">
        <ORIGINAL_TEXT>&lt;/P&gt;</ORIGINAL_TEXT>
        <TOKEN id="token-27-0" pos="unknown" morph="none" start_char="782" end_char="785">&lt;/P&gt;</TOKEN>
      </SEG>
      <SEG id="segment-28" start_char="787" end_char="789">
        <ORIGINAL_TEXT>&lt;P&gt;</ORIGINAL_TEXT>
        <TOKEN id="token-28-0" pos="unknown" morph="none" start_char="787" end_char="789">&lt;P&gt;</TOKEN>
      </SEG>
      <SEG id="segment-29" start_char="791" end_char="859">
        <ORIGINAL_TEXT>　　聯合國安理會3日發表聲明，以“最強烈的言辭”譴責索馬里宗教極端組織“青年黨”襲擊肯尼亞加里薩市莫伊大學，強調要打擊一切形式的恐怖主義。</ORIGINAL_TEXT>
        <TOKEN id="token-29-0" pos="unknown" morph="none" start_char="791" end_char="859">　　聯合國安理會3日發表聲明，以“最強烈的言辭”譴責索馬里宗教極端組織“青年黨”襲擊肯尼亞加里薩市莫伊大學，強調要打擊一切形式的恐怖主義。</TOKEN>
      </SEG>
      <SEG id="segment-30" start_char="861" end_char="864">
        <ORIGINAL_TEXT>&lt;/P&gt;</ORIGINAL_TEXT>
        <TOKEN id="token-30-0" pos="unknown" morph="none" start_char="861" end_char="864">&lt;/P&gt;</TOKEN>
      </SEG>
      <SEG id="segment-31" start_char="866" end_char="868">
        <ORIGINAL_TEXT>&lt;P&gt;</ORIGINAL_TEXT>
        <TOKEN id="token-31-0" pos="unknown" morph="none" start_char="866" end_char="868">&lt;P&gt;</TOKEN>
      </SEG>
      <SEG id="segment-32" start_char="870" end_char="978">
        <ORIGINAL_TEXT>　　聲明說，安理會向遇害者家人、肯尼亞人民和政府致以慰問。安理會讚賞肯尼亞在打擊恐怖主義及其在非盟駐索馬里特派團打擊“青年黨”方面所發揮的作用。安理會強調必須將這一恐怖主義行徑的實施者、組織者、資助者和支持者繩之以法。</ORIGINAL_TEXT>
        <TOKEN id="token-32-0" pos="unknown" morph="none" start_char="870" end_char="978">　　聲明說，安理會向遇害者家人、肯尼亞人民和政府致以慰問。安理會讚賞肯尼亞在打擊恐怖主義及其在非盟駐索馬里特派團打擊“青年黨”方面所發揮的作用。安理會強調必須將這一恐怖主義行徑的實施者、組織者、資助者和支持者繩之以法。</TOKEN>
      </SEG>
      <SEG id="segment-33" start_char="980" end_char="983">
        <ORIGINAL_TEXT>&lt;/P&gt;</ORIGINAL_TEXT>
        <TOKEN id="token-33-0" pos="unknown" morph="none" start_char="980" end_char="983">&lt;/P&gt;</TOKEN>
      </SEG>
      <SEG id="segment-34" start_char="985" end_char="991">
        <ORIGINAL_TEXT>&lt;/TEXT&gt;</ORIGINAL_TEXT>
        <TOKEN id="token-34-0" pos="unknown" morph="none" start_char="985" end_char="991">&lt;/TEXT&gt;</TOKEN>
      </SEG>
      <SEG id="segment-35" start_char="993" end_char="998">
        <ORIGINAL_TEXT>&lt;/DOC&gt;</ORIGINAL_TEXT>
        <TOKEN id="token-35-0" pos="unknown" morph="none" start_char="993" end_char="998">&lt;/DOC&gt;</TOKEN>
      </SEG>
    </TEXT>
  </DOC>
</LCTL_TEXT>
